django_extensible_forms/__init__.py
django_extensible_forms/boundfield.py
django_extensible_forms/fields.py
django_extensible_forms/forms.py
django_extensible_forms/models.py
django_extensible_forms/mutators.py
django_extensible_forms/renderers.py
django_extensible_forms/tests.py
django_extensible_forms/utils.py
django_extensible_forms/widgets.py
django_extensible_forms/bootstrap5/__init__.py
django_extensible_forms/bootstrap5/boundfield.py
django_extensible_forms/bootstrap5/fields.py
django_extensible_forms/bootstrap5/forms.py
django_extensible_forms/bootstrap5/models.py
django_extensible_forms/bootstrap5/mutators.py
django_extensible_forms/bootstrap5/utils.py
django_extensible_forms/bootstrap5/widgets.py
django_extensible_forms/bootstrap5/templatetags/__init__.py
django_extensible_forms/bootstrap5/templatetags/bootstrap5.py
django_extensible_forms/templates/django/forms/attrs.html
django_extensible_forms/templates/django/forms/widgets/attrs.html
django_extensible_forms/templates/django_extensible_forms/bootstrap5_forms/boolean_field.html
django_extensible_forms/templates/django_extensible_forms/bootstrap5_forms/widgets/wrappers/input_group_wrapper.html
django_extensible_forms/templates/django_extensible_forms/forms/div.html
django_extensible_forms/templates/django_extensible_forms/forms/field.html
django_extensible_forms/templates/django_extensible_forms/forms/errors/dict/field_default.html
django_extensible_forms/templates/django_extensible_forms/forms/errors/dict/field_div.html
django_extensible_forms/templates/django_extensible_forms/forms/errors/dict/field_ul.html
django_extensible_forms/templates/django_extensible_forms/forms/errors/list/field_default.html
django_extensible_forms/templates/django_extensible_forms/forms/errors/list/field_div.html
django_extensible_forms/templates/django_extensible_forms/forms/errors/list/field_ul.html
django_extensible_forms/templates/django_extensible_forms/forms/widgets/range.html
django_extensible_forms-0.9.1.dist-info/METADATA
django_extensible_forms-0.9.1.dist-info/WHEEL
django_extensible_forms-0.9.1.dist-info/licenses/LICENSE
django_extensible_forms-0.9.1.dist-info/RECORD
