Metadata-Version: 2.1
Name: django-extensible-forms
Version: 0.9.1
Summary: Sensible form extensions for django.
Project-URL: Homepage, https://github.com/naggafin/django-extensible-forms
Project-URL: Bug Tracker, https://github.com/naggafin/django-extensible-forms/issues
Author-email: naggafin <nevincoutu@gmail.com>
License-File: LICENSE
Classifier: Development Status :: 4 - Beta
Classifier: Framework :: Django
Classifier: License :: OSI Approved :: MIT License
Classifier: Operating System :: OS Independent
Classifier: Programming Language :: Python :: 3
Requires-Python: >=3.7
Requires-Dist: django>=3.2
